README.rst
setup.py
formsteps/__init__.py
formsteps/forms.py
formsteps/serializers.py
formsteps/utils.py
formsteps.egg-info/PKG-INFO
formsteps.egg-info/SOURCES.txt
formsteps.egg-info/dependency_links.txt
formsteps.egg-info/requires.txt
formsteps.egg-info/top_level.txt