Metadata-Version: 1.0
Name: formsteps
Version: 0.1.0
Summary: Simple Step Forms Library
Home-page: https://github.com/gisce/formsteps
Author: GISCE-TI, S.L.
Author-email: devel@gisce.net
License: MIT
Platform: UNKNOWN
